README.rst
setup.py
tkp/__init__.py
tkp/inject.py
tkp/main.py
tkp/management.py
tkp.egg-info/PKG-INFO
tkp.egg-info/SOURCES.txt
tkp.egg-info/dependency_links.txt
tkp.egg-info/requires.txt
tkp.egg-info/top_level.txt
tkp/accessors/__init__.py
tkp/accessors/aartfaaccasaimage.py
tkp/accessors/amicasaimage.py
tkp/accessors/casaimage.py
tkp/accessors/dataaccessor.py
tkp/accessors/detection.py
tkp/accessors/fitsimage.py
tkp/accessors/kat7casaimage.py
tkp/accessors/lofaraccessor.py
tkp/accessors/lofarcasaimage.py
tkp/accessors/lofarfitsimage.py
tkp/accessors/lofarhdf5image.py
tkp/accessors/requiredatts.py
tkp/bin/__init__.py
tkp/bin/pyse.py
tkp/bin/tkp-inject.py
tkp/bin/trap-manage.py
tkp/config/__init__.py
tkp/config/parse.py
tkp/config/job_template/images_to_process.py
tkp/config/job_template/inject.cfg
tkp/config/job_template/job_params.cfg
tkp/config/project_template/README.rst
tkp/config/project_template/pipeline.cfg
tkp/db/__init__.py
tkp/db/alchemy.py
tkp/db/associations.py
tkp/db/configstore.py
tkp/db/consistency.py
tkp/db/database.py
tkp/db/dump.py
tkp/db/general.py
tkp/db/generic.py
tkp/db/model.py
tkp/db/monitoringlist.py
tkp/db/nulldetections.py
tkp/db/orm.py
tkp/db/quality.py
tkp/db/sql/__init__.py
tkp/db/sql/populate.py
tkp/db/sql/preprocessor.py
tkp/db/sql/upgrade.py
tkp/db/sql/statements/batch
tkp/db/sql/statements/functions/alpha.sql
tkp/db/sql/statements/functions/cartesian.sql
tkp/db/sql/statements/functions/degrad.sql
tkp/db/sql/statements/functions/getBand.sql
tkp/db/sql/statements/functions/getSkyRgn.sql
tkp/db/sql/statements/functions/insertDataset.sql
tkp/db/sql/statements/functions/insertImage.sql
tkp/db/sql/statements/functions/median.sql
tkp/db/sql/statements/functions/updateSkyRgnMembers.sql
tkp/db/sql/statements/init/tables.sql
tkp/db/sql/statements/procedures/BuildFrequencyBands.sql
tkp/db/sql/statements/procedures/BuildNodes.sql
tkp/db/sql/statements/views/augmented_runningcatalog.sql
tkp/distribute/__init__.py
tkp/distribute/multiproc/__init__.py
tkp/distribute/multiproc/tasks.py
tkp/distribute/serial/__init__.py
tkp/distribute/serial/tasks.py
tkp/quality/__init__.py
