Metadata-Version: 1.0
Name: tkp
Version: 3.1.1
Summary: LOFAR Transients Key Project (TKP)
Home-page: http://docs.transientskp.org/
Author: TKP Discovery WG
Author-email: discovery@transientskp.org
License: UNKNOWN
Platform: UNKNOWN
